comicepub/__init__.py
comicepub/__version__.py
comicepub/cli.py
comicepub/comicepub.py
comicepub/render.py
comicepub/template/container.xml
comicepub/template/cover.xhtml
comicepub/template/fixed-layout-jp.css
comicepub/template/mimetype
comicepub/template/navigation-documents.xhtml
comicepub/template/p.xhtml
comicepub/template/standard.opf
comicepub-0.2.4.dist-info/LICENSE
comicepub-0.2.4.dist-info/METADATA
comicepub-0.2.4.dist-info/WHEEL
comicepub-0.2.4.dist-info/entry_points.txt
comicepub-0.2.4.dist-info/top_level.txt
comicepub-0.2.4.dist-info/RECORD
