Metadata-Version: 2.1
Name: comicepub
Version: 0.2.4
Summary: Japanese comic EPUB3 generate tool
Author-email: ShinCurry <shincurryyang@gmail.com>
License: MIT License
Project-URL: Homepage, https://github.com/moeoverflow/comicepub
Project-URL: Source, https://github.com/pypa/comicepub/
Classifier: Programming Language :: Python :: 3
Classifier: License :: OSI Approved :: MIT License
Classifier: Operating System :: OS Independent
Requires-Python: <3.13,>=3.7
License-File: LICENSE
Requires-Dist: Jinja2 >=2.10.1
